pyerrorhelper/__init__.py
pyerrorhelper/base.py
pyerrorhelper/manager.py
pyerrorhelper/ollamembedder.py
pyerrorhelper-0.2.5.dist-info/licenses/LICENSE
pyerrorhelper-0.2.5.dist-info/METADATA
pyerrorhelper-0.2.5.dist-info/WHEEL
pyerrorhelper-0.2.5.dist-info/top_level.txt
pyerrorhelper-0.2.5.dist-info/RECORD
