Metadata-Version: 2.4
Name: pyerrorhelper
Version: 0.2.5
Summary: AI enabled error handling library
Author-email: Shikhar Aditya <satyamshikhar@gmail.com>
License: MIT
Keywords: error-handling,middleware,python,ai,ai-error-handling,ai-error-summarization
Requires-Python: >=3.8
License-File: LICENSE
Dynamic: license-file
